deepair/__init__.py
deepair/common/__init__.py
deepair/common/replay.py
deepair/common/utils.py
deepair/dqn/__init__.py
deepair/dqn/dqn.py
deepair/dqn/layer.py
deepair/dqn/network.py
tests/__init__.py
deepair-0.1.dist-info/LICENSE
deepair-0.1.dist-info/METADATA
deepair-0.1.dist-info/WHEEL
deepair-0.1.dist-info/entry_points.txt
deepair-0.1.dist-info/top_level.txt
deepair-0.1.dist-info/RECORD
